instantview/__init__.py
instantview/__main__.py
instantview/_version.py
instantview/hooks.py
instantview/web.py
instantview-0.1.1.dist-info/LICENSE
instantview-0.1.1.dist-info/METADATA
instantview-0.1.1.dist-info/WHEEL
instantview-0.1.1.dist-info/entry_points.txt
instantview-0.1.1.dist-info/top_level.txt
instantview-0.1.1.dist-info/RECORD
