Metadata-Version: 2.1
Name: instantview
Version: 0.1.1
Summary: Delta Chat bot to take website screenshots
Author-email: adbenitez <adb@merlinux.eu>
Project-URL: Homepage, https://github.com/deltachat-bot/instantview
Keywords: deltachat,bot
Classifier: Development Status :: 4 - Beta
Classifier: Programming Language :: Python
Classifier: License :: OSI Approved :: GNU General Public License v3 or later (GPLv3+)
Requires-Python: >=3.8
License-File: LICENSE
Requires-Dist: deltabot-cli <7.0,>=6.2.0
Requires-Dist: beautifulsoup4 <5.0,>=4.12.3
Requires-Dist: html5lib <2.0,>=1.1
Requires-Dist: requests <3.0,>=2.32.3
Provides-Extra: dev
Requires-Dist: black ; extra == 'dev'
Requires-Dist: mypy ; extra == 'dev'
Requires-Dist: isort ; extra == 'dev'
Requires-Dist: pylint ; extra == 'dev'
Requires-Dist: pylama ; extra == 'dev'
Requires-Dist: pytest ; extra == 'dev'
Requires-Dist: types-requests ; extra == 'dev'
